{
  "posts": [
    {
      "locale": "en-US",
      "title": "Sample Title For the First Blog Post in English",
      "description": "This is the first blog post in English published on the blog",
      "image": "https://www.datocms-assets.com/54676/1612503497-ferran-feixas-ubflzcoxst8-unsplash.jpg"
    },
    {
      "locale": "en-US",
      "title": "Sample Title For the Second Blog Post in English",
      "description": "This is the second blog post in English published on the blog",
      "image": "https://www.datocms-assets.com/54676/1612503265-manuel-meurisse-eucll-f5ati-unsplash.jpg"
    },
    {
      "locale": "es-ES",
      "title": "Título de ejemplo para la primera entrada en español del blog",
      "description": "Esta es la primera entrada del blog en español publicada en el blog",
      "image": "https://www.datocms-assets.com/54676/1612503497-ferran-feixas-ubflzcoxst8-unsplash.jpg"
    },
    {
      "locale": "es-ES",
      "title": "Título de ejemplo para la segunda entrada en español del blog",
      "description": "Esta es la segunda entrada del blog en español publicada en el blog",
      "image": "https://www.datocms-assets.com/54676/1612503265-manuel-meurisse-eucll-f5ati-unsplash.jpg"
    },
    {
      "locale": "pt-BR",
      "title": "Título de exemplo para a primeira entrada do blog em português",
      "description": "Esta é a primeira entrada de blog em português publicada no blog",
      "image": "https://www.datocms-assets.com/54676/1612503156-clay-banks-hwlai5lrhdm-unsplash.jpg"
    },
    {
      "locale": "pt-BR",
      "title": "Título de exemplo para a segunda entrada do blog em português",
      "description": "Esta é a segunda entrada de blog em português publicada no blog",
      "image": "https://www.datocms-assets.com/54676/1612503156-clay-banks-hwlai5lrhdm-unsplash.jpg"
    }
  ]
}
